soft_remover/__init__.py
soft_remover/managers.py
soft_remover/models.py
soft_remover/locale/en/LC_MESSAGES/django.mo
soft_remover/locale/en/LC_MESSAGES/django.po
soft_remover/locale/ru/LC_MESSAGES/django.mo
soft_remover/locale/ru/LC_MESSAGES/django.po
soft_remover/migrations/__init__.py
django_soft_remover-0.5.0.dist-info/LICENSE
django_soft_remover-0.5.0.dist-info/METADATA
django_soft_remover-0.5.0.dist-info/WHEEL
django_soft_remover-0.5.0.dist-info/top_level.txt
django_soft_remover-0.5.0.dist-info/RECORD
